{"{url}/{i}": {"path": "DaLi2022/IMG_5034.jpeg", "dir": "DaLi2022", "exif": "Apple iPhone 12 Pro 1/149s F2 ISO 25 6mm iPhone 12 Pro back triple camera 6mm f/2 ", "location": [], "name": "IMG_5034", "desc": " - · - ", "exif_data": {"Image Make": "Apple", "Image Model": "iPhone 12 Pro", "EXIF ExposureTime": "1/149s", "EXIF FNumber": "F2", "EXIF ISOSpeedRatings": "ISO 25", "EXIF DateTimeOriginal": "2022:10:06 17:19:14", "EXIF FocalLength": "6mm", "EXIF LensModel": "iPhone 12 Pro back triple camera 6mm f/2"}}}